librbac/__init__.py
librbac/apps.py
librbac/manager.py
librbac/contrib/__init__.py
librbac/contrib/migrations/README.md
librbac/contrib/migrations/__init__.py
librbac/contrib/migrations/apps.py
librbac/contrib/migrations/config.py
librbac/contrib/migrations/models.py
librbac/contrib/migrations/orchestrator.py
librbac/contrib/migrations/types.py
librbac/contrib/migrations/domain/__init__.py
librbac/contrib/migrations/domain/events.py
librbac/contrib/migrations/loader/__init__.py
librbac/contrib/migrations/loader/disk.py
librbac/contrib/migrations/management/__init__.py
librbac/contrib/migrations/management/commands/__init__.py
librbac/contrib/migrations/management/commands/rbac_migrate.py
librbac/contrib/migrations/migrations/0001_initial.py
librbac/contrib/migrations/migrations/__init__.py
librbac/contrib/migrations/recorder/__init__.py
librbac/contrib/migrations/recorder/local_db.py
librbac/contrib/migrations/services/__init__.py
librbac/contrib/migrations/services/handlers.py
librbac/contrib/oidc/__init__.py
librbac/contrib/oidc/auth.py
librbac/contrib/oidc/types.py
librbac/contrib/oidc/utis.py
librbac/domain/__init__.py
librbac/domain/events.py
librbac/domain/permissions.py
librbac/domain/interfaces/__init__.py
librbac/domain/interfaces/backend.py
librbac/domain/interfaces/collector.py
librbac/domain/interfaces/publisher.py
librbac/infrastructure/__init__.py
librbac/infrastructure/explicit/__init__.py
librbac/infrastructure/explicit/publisher.py
librbac/infrastructure/rest_framework/__init__.py
librbac/infrastructure/rest_framework/backend.py
librbac/infrastructure/rest_framework/collector.py
librbac/infrastructure/rest_framework/domain.py
librbac/infrastructure/rest_framework/permissions.py
librbac/infrastructure/rest_framework/types.py
librbac/infrastructure/rest_framework/utils.py
librbac/infrastructure/rest_framework/viewsets.py
librbac/management/__init__.py
librbac/management/commands/__init__.py
librbac/management/commands/rbac.py
librbac-3.0.2.dist-info/LICENSE
librbac-3.0.2.dist-info/METADATA
librbac-3.0.2.dist-info/WHEEL
librbac-3.0.2.dist-info/dependency_links.txt
librbac-3.0.2.dist-info/top_level.txt
librbac-3.0.2.dist-info/RECORD
