Metadata-Version: 2.1
Name: librbac
Version: 3.0.2
Summary: Общая библиотека контроля доступа для микросервисов
Home-page: https://stash.bars-open.ru/projects/EDUEO/repos/librbac/
Author: BARS Group
Author-email: education_dev@bars-open.ru
Classifier: Intended Audience :: Developers
Classifier: Environment :: Web Environment
Classifier: Natural Language :: Russian
Classifier: Natural Language :: English
Classifier: Operating System :: OS Independent
Classifier: Development Status :: 3 - Alpha
Classifier: Programming Language :: Python
Classifier: Programming Language :: Python :: 3.10
Classifier: Programming Language :: Python :: 3.11
Classifier: Programming Language :: Python :: 3.12
Classifier: Framework :: Django :: 4.0
Classifier: Framework :: Django :: 4.1
Classifier: Framework :: Django :: 4.2
Classifier: Framework :: Django :: 5.0
Classifier: Framework :: Django :: 5.1
License-File: LICENSE
Requires-Dist: explicit-python <3.0,>=1.3.0
Requires-Dist: django
Requires-Dist: pydantic <2.0
